LICENSE
MANIFEST.in
README.rst
setup.py
camxes/__init__.py
camxes/__main__.py
camxes/camxes.jar
camxes/tests.py
camxes.egg-info/PKG-INFO
camxes.egg-info/SOURCES.txt
camxes.egg-info/dependency_links.txt
camxes.egg-info/not-zip-safe
camxes.egg-info/requires.txt
camxes.egg-info/top_level.txt