Metadata-Version: 1.0
Name: camxes
Version: 0.1
Summary: Python interface to camxes.
Home-page: https://github.com/dag/python-camxes
Author: Dag Odenhall
Author-email: dag.odenhall@gmail.com
License: Simplified BSD
Platform: UNKNOWN
Classifier: Development Status :: 4 - Beta
Classifier: Intended Audience :: Developers
Classifier: Intended Audience :: Science/Research
Classifier: License :: OSI Approved :: BSD License
Classifier: Programming Language :: Java
Classifier: Programming Language :: Python
Classifier: Programming Language :: Python :: 2.6
Classifier: Programming Language :: Python :: 2.7
Classifier: Programming Language :: Python :: 3.1
Classifier: Topic :: Scientific/Engineering :: Artificial Intelligence
Classifier: Topic :: Scientific/Engineering :: Human Machine Interfaces
Classifier: Topic :: Text Processing :: Linguistic
